trustpilot/__init__.py
trustpilot/async_client.py
trustpilot/auth.py
trustpilot/cli.py
trustpilot/client.py
trustpilot/utils.py
trustpilot-10.0.1.dist-info/LICENSE
trustpilot-10.0.1.dist-info/METADATA
trustpilot-10.0.1.dist-info/WHEEL
trustpilot-10.0.1.dist-info/entry_points.txt
trustpilot-10.0.1.dist-info/RECORD
