Metadata-Version: 2.1
Name: trustpilot
Version: 10.0.1
Summary: Trustpilot API client including CLI tool
Home-page: https://github.com/trustpilot/python-trustpilot
License: MIT
Keywords: trustpilot,api,client
Author: John Sutherland
Author-email: johns@trustpilot.com
Requires-Python: >=3.8,<4.0
Classifier: Development Status :: 5 - Production/Stable
Classifier: Intended Audience :: Developers
Classifier: License :: OSI Approved :: MIT License
Classifier: Natural Language :: English
Classifier: Programming Language :: Python :: 3
Classifier: Programming Language :: Python :: 3.8
Classifier: Programming Language :: Python :: 3.9
Classifier: Programming Language :: Python :: 3.10
Classifier: Programming Language :: Python :: 3.11
Classifier: Programming Language :: Python :: 3.7
Requires-Dist: aiohttp (>=3.8.5,<4.0.0)
Requires-Dist: click (>=8.1.6,<9.0.0)
Requires-Dist: requests (>=2.31.0,<3.0.0)
Project-URL: Repository, https://github.com/trustpilot/python-trustpilot
